jet/__init__.py
jet/bilaplacian.py
jet/jet_transformer.py
jet/laplacian.py
jet/operations.py
jet/rules.py
jet/signature_parser.py
jet/simplify.py
jet/tracing.py
jet/ttc_coefficients.py
jet/utils.py
jet/vmap.py
jet/weighted_laplacian.py
jet/exp/__init__.py
jet/exp/utils.py
jet/exp/exp01_benchmark_laplacian/__init__.py
jet/exp/exp01_benchmark_laplacian/evaluate_performance.py
jet/exp/exp01_benchmark_laplacian/execute.py
jet/exp/exp01_benchmark_laplacian/plot.py
jet/exp/exp01_benchmark_laplacian/run.py
jet/exp/exp01_benchmark_laplacian/figures/architecture_tanh_mlp_768_768_512_512_1_batch_size_2048_compiled_cuda_dim_50_normal_name_weighted_laplacian_vary_num_samples_rank_ratio_1_0.pdf
jet/exp/exp01_benchmark_laplacian/figures/architecture_tanh_mlp_768_768_512_512_1_batch_size_2048_compiled_device_cuda_dim_50_distribution_normal_name_laplacian_vary_num_samples.pdf
jet/exp/exp01_benchmark_laplacian/figures/architecture_tanh_mlp_768_768_512_512_1_batch_size_2048_compiled_device_cuda_dim_50_name_weighted_laplacian_vary_rank_ratio.pdf
jet/exp/exp01_benchmark_laplacian/figures/architecture_tanh_mlp_768_768_512_512_1_batch_size_2048_cuda_dim_50_normal_name_weighted_laplacian_vary_num_samples_rank_ratio_1_0.pdf
jet/exp/exp01_benchmark_laplacian/figures/architecture_tanh_mlp_768_768_512_512_1_batch_size_2048_device_cuda_dim_50_distribution_normal_name_laplacian_vary_num_samples.pdf
jet/exp/exp01_benchmark_laplacian/figures/architecture_tanh_mlp_768_768_512_512_1_batch_size_2048_device_cuda_dim_50_name_weighted_laplacian_vary_rank_ratio.pdf
jet/exp/exp01_benchmark_laplacian/figures/architecture_tanh_mlp_768_768_512_512_1_batch_size_256_compiled_device_cuda_dim_5_distribution_normal_name_bilaplacian_vary_num_samples.pdf
jet/exp/exp01_benchmark_laplacian/figures/architecture_tanh_mlp_768_768_512_512_1_batch_size_256_device_cuda_dim_5_distribution_normal_name_bilaplacian_vary_num_samples.pdf
jet_for_pytorch-0.0.1.dist-info/licenses/LICENSE
jet_for_pytorch-0.0.1.dist-info/METADATA
jet_for_pytorch-0.0.1.dist-info/WHEEL
jet_for_pytorch-0.0.1.dist-info/top_level.txt
jet_for_pytorch-0.0.1.dist-info/RECORD
