Metadata-Version: 2.4
Name: jet-for-pytorch
Version: 0.0.1
Summary: Taylor-mode automatic differentiation for PyTorch
Author: Felix Dangel, Tim Siebert, Marius Zeinhofer, Andrea Walther
License: MIT
Project-URL: Repository, https://github.com/f-dangel/torch-jet
Classifier: Development Status :: 3 - Alpha
Classifier: License :: OSI Approved :: MIT License
Classifier: Operating System :: OS Independent
Classifier: Programming Language :: Python :: 3.12
Requires-Python: >=3.12
License-File: LICENSE
Requires-Dist: torch
Requires-Dist: einops
Requires-Dist: numpy
Requires-Dist: scipy
Requires-Dist: pyyaml
Provides-Extra: exp
Requires-Dist: memory_profiler; extra == "exp"
Requires-Dist: pandas; extra == "exp"
Requires-Dist: matplotlib; extra == "exp"
Requires-Dist: tueplots; extra == "exp"
Requires-Dist: jax; extra == "exp"
Requires-Dist: jaxlib; extra == "exp"
Requires-Dist: folx; extra == "exp"
Requires-Dist: arxiv-collector; extra == "exp"
Provides-Extra: test
Requires-Dist: coveralls; extra == "test"
Requires-Dist: pytest; extra == "test"
Requires-Dist: pytest-cov; extra == "test"
Provides-Extra: lint
Requires-Dist: ruff; extra == "lint"
Provides-Extra: doc
Requires-Dist: matplotlib; extra == "doc"
Requires-Dist: mkdocs==1.6.1; extra == "doc"
Requires-Dist: mkdocs-material==9.6.13; extra == "doc"
Requires-Dist: mkdocstrings[python]==0.30.0; extra == "doc"
Requires-Dist: mkdocs-gallery==0.10.4; extra == "doc"
Requires-Dist: pydot; extra == "doc"
Requires-Dist: pytest; extra == "doc"
Requires-Dist: tueplots; extra == "doc"
Requires-Dist: ruff; extra == "doc"
Dynamic: license-file
